cqp_tree/__init__.py
cqp_tree/utils.py
cqp_tree/cli/__init__.py
cqp_tree/cli/main.py
cqp_tree/frontends/__init__.py
cqp_tree/frontends/conll/__init__.py
cqp_tree/frontends/conll/translator.py
cqp_tree/frontends/deptreepy/__init__.py
cqp_tree/frontends/deptreepy/translator.py
cqp_tree/frontends/grew/__init__.py
cqp_tree/frontends/grew/translator.py
cqp_tree/frontends/grew/antlr/GrewLexer.py
cqp_tree/frontends/grew/antlr/GrewParser.py
cqp_tree/frontends/grew/antlr/__init__.py
cqp_tree/translation/__init__.py
cqp_tree/translation/cqp.py
cqp_tree/translation/errors.py
cqp_tree/translation/query.py
cqp_tree/translation/regex.py
cqp_tree/translation/registry.py
cqp_tree/web/__init__.py
cqp_tree/web/app.py
cqp_tree/web/server.py
cqp_tree/web/static/index.html
cqp_tree-0.1a1.dist-info/licenses/LICENSE.txt
cqp_tree-0.1a1.dist-info/METADATA
cqp_tree-0.1a1.dist-info/WHEEL
cqp_tree-0.1a1.dist-info/entry_points.txt
cqp_tree-0.1a1.dist-info/top_level.txt
cqp_tree-0.1a1.dist-info/RECORD
