Metadata-Version: 2.4
Name: cqp-tree
Version: 0.1a1
Summary: Translate queries from tree-based formats to sequential CQP format used by Corpus Workbench.
Author: Niklas Deworetzki, Arianna Masciolini
License-Expression: MPL-2.0
Project-URL: Homepage, https://github.com/Niklas-Deworetzki/cqp-tree
Project-URL: Issues, https://github.com/Niklas-Deworetzki/cqp-tree/issues
Keywords: corpus search,query translation,corpus workbench,korp
Classifier: Development Status :: 3 - Alpha
Classifier: Intended Audience :: Developers
Classifier: Intended Audience :: Science/Research
Classifier: Topic :: Scientific/Engineering :: Interface Engine/Protocol Translator
Classifier: Topic :: Text Processing :: Linguistic
Classifier: Typing :: Typed
Requires-Python: <4,>=3.12
License-File: LICENSE.txt
Requires-Dist: antlr4-python3-runtime==4.13.2
Requires-Dist: pyparsing==3.2.5
Requires-Dist: conllu==6.0.0
Requires-Dist: Flask==3.1.2
Dynamic: license-file
